digRandomIndexingExtractor
