Metadata-Version: 1.1
Name: digRandomIndexingExtractor
Version: 0.2.0
Summary: digRandomIndexingExtractor
Home-page: https://github.com/usc-isi-i2/dig-random-indexing-extractor
Author: Jason Slepicka
Author-email: jasonslepicka@gmail.com
License: UNKNOWN
Download-URL: https://github.com/usc-isi-i2/dig-random-indexing-extractor
Platform: UNKNOWN
